{
  "id": "back-rank-03",
  "fen": "r5k1/5ppp/8/8/8/8/5PPP/R5K1 w - - 0 1",
  "solution": [
    "Rxa8#"
  ],
  "title": "ルークが消えれば詰み",
  "setup": "a列でルーク同士がにらみ合う対称形。黒キングには逃げ場がありません。",
  "hint": "ルークを交換しましょう。黒のポーンの壁は、同時に黒の檻でもあります。",
  "explanation": "## 狙い\n\n{{Rxa8#}} は **交換から詰みへ** という、最もシンプルで美しいバックランクの実行形です。\n\n### 一手ずつ見ていく\n\n1. 白のルークがa8の黒ルークを取ります。\n2. 黒には取り返す駒がありません（g8のキングは遠く、8段目に他の守り手はいません）。\n3. キングはa8の白ルークから8段目全体に沿ってチェックを受けています。\n4. **逃げ場なし：** g7-h7は自分のポーン、h8/f8は白ルークに攻撃され、取る駒も合駒も残っていません。\n\n### 黒が以前にやるべきだったこと\n\n- ずっと前に {{h6}} か {{g6}} を突いてキングに空気を与えておく。\n- 駒（ナイト、ビショップ、クイーン）でバックランクを守り続ける。\n- キングにルフトがないときに、開いた列でのルーク交換を避ける。\n\n> 同等の戦力 + ポーン構造の1テンポの差 = 一方が勝ちます。バックランクメイトは、ルフトを怠った代償なのです。"
}
