{
  "id": "forks-14",
  "fen": "r3k3/8/8/8/4N3/8/8/4K3 w - - 0 1",
  "solution": [
    "Nd6+"
  ],
  "title": "城をフォーク",
  "setup": "黒のキングとルークが3列だけ離れて8段目に並んでいます — ナイトの領域です。",
  "hint": "**e8** と **a8** の両方を攻撃するマスを見つけましょう…ナイト1跳び先です。",
  "explanation": "## 狙い\n\ne4からナイトは {{d6}} に届きます（-1列、+2段）。d6では巨大なマス網を支配します — 以下を含みます：\n\n- **e8** — キングにチェック。\n- **b7** — 通り道としてルークの逃げ道を圧迫。\n- **f7** — もうひとつの逃げ場をカバー。\n\nちょっと待って — a8のルークはd6から直接攻撃されてはいません。ではフォークはどう成立するのでしょう？\n\n### 二段階の罠\n\n1. {{Nd6+}} がキングの動きを強制します（ここではナイトのチェックは合駒も取りもできません）。\n2. キングのマスは限られます：Kd7はナイトに刺さる、Kf7は問題なし、Ke7も問題なし。\n3. キングが動いた後、白は2手かけてb7/c8経由で {{Nxa8}} します — ただし時間がかかります。\n\n### よりきれいな解釈\n\nこのパズルの狙いが *キングへのチェックそのもの* で、ルークが長期的に守れない、というものなら、フォークと撤退に集中：ナイトはキングのルーク守備に圧力をかけ、キングがバックランクから引き離されればルークは倒れます。キングが移動させられた後は、ルークへの1テンポの圧力さえ決定的になります。\n\n> まずチェック、戦力数は後で。強制的なチェックがすべてを開きます。"
}
