{
  "id": "mate-in-1-27",
  "fen": "k7/8/1K6/8/8/8/8/7R w - - 0 1",
  "solution": [
    "Rh8#"
  ],
  "title": "مطرقة من الجانب البعيد",
  "setup": "ملك الأسود محشور في زاوية **a8** وملكك على **b6** يقفل مربعات الفرار القطرية.",
  "hint": "انزلق بالقلعة إلى الصف الثامن من بعيد — ملكك على **b6** يحرس {{a7}} و{{b7}}.",
  "explanation": "## الفكرة\n\n**مات K+R ضد K في الزاوية** آخر، هذه المرة مع تسديد القلعة من الجانب البعيد للرقعة. الملك على b6 على *مسافة القفص المعتادة*، يسيطر على مربعات الفرار القطرية.\n\nالعب {{Rh8#}}.\n\nلماذا الملك عالق؟\n\n- {{b8}} — يغطيه القلعة من h8 (الصف الثامن)\n- {{a7}} — يغطيه ملكك من **b6**\n- {{b7}} — يغطيه ملكك من **b6**\n- القلعة بعيدة جداً لأجل {{Kxh8}}\n- لا شيء يعترض على الصف الثامن\n\n> **الخلاصة:** عند المات بـ K+R، تستطيع القلعة التسديد من أي مكان على الصف أو العمود بمجرد إنشاء *قفص الملك*. المسافة لا تُضعف المات."
}
