{
  "id": "mate-in-2-03",
  "fen": "8/8/8/8/8/1K6/8/k5R1 w - - 0 1",
  "solution": [
    "Rg2",
    "Kb1",
    "Rg1#"
  ],
  "title": "Сжатие цугцвангом",
  "setup": "Чёрный король в углу **a1**. Ваш король на **b3** держит {{a2}} и {{b2}} — но у чёрных ещё есть тихий выход на {{b1}}.",
  "hint": "Не шахуйте сразу — сделайте *выжидательный ход*, контролирующий 2-ю горизонталь, и вынудите короля на {{b1}}.",
  "explanation": "## Идея\n\n**Мат в два хода с тихим первым ходом.** Хитрость в том, что немедленный шах ладьёй позволяет королю пройти на **b1** без матового продолжения, а *выжидательный ход* ставит чёрных в **цугцванг** — чёрные сами заходят под мат.\n\n**1. {{Rg2}}** — ладья выходит на 2-ю горизонталь. Это *не* шах, но контролирует всю 2-ю горизонталь.\n\n**1...{{Kb1}}** — вынужденно. Единственный легальный ход: {{Ka2}} и {{Kb2}} атакованы вашим королём на **b3**, а на a1 у короля нет других ходов, кроме b1.\n\n**2. {{Rg1#}}** — ладья опускается на 1-ю горизонталь, ставя мат.\n\nПочему король заперт после второго хода?\n\n- {{a1}} — под боем ладьи на g1 (1-я горизонталь)\n- {{c1}} — под боем ладьи на g1 (1-я горизонталь)\n- {{a2}} — контролируется вашим королём на **b3**\n- {{b2}} — контролируется вашим королём на **b3**\n- {{c2}} — контролируется вашим королём на **b3**\n- Ладья слишком далеко для {{Kxg1}}\n\n> **Вывод:** Не каждый мат начинается с шаха. **Цугцванг** — один из красивейших инструментов шахматных эндшпилей: иногда сильнейший ход — *не делать ничего агрессивного*, заставляя соперника сделать проигрывающий ход."
}
