{
  "id": "mate-in-1-12",
  "fen": "7k/2Q4p/6K1/8/8/8/8/8 w - - 0 1",
  "solution": [
    "Qxh7#"
  ],
  "title": "Возьми пешку — возьми короля",
  "setup": "Ваш ферзь сметает 7-ю горизонталь, а король на **g6** в шаге от событий.",
  "hint": "Возьмите пешку {{h7}} — ваш король защищает ферзя, и чёрным некуда бежать.",
  "explanation": "## Идея\n\nКлассический **угловой поцелуй смерти**. Ферзь забирает единственную пешку, защищающую короля, и приземляется на поле под защитой собственного короля.\n\nИграйте {{Qxh7#}}.\n\nПочему король заперт?\n\n- Ферзь на h7 атакует h8 напрямую (шах).\n- {{g8}} — под боем ферзя h7 (диагональ).\n- {{Kxh7}} нелегально — ваш король **g6** защищает h7.\n- Закрыться нечем: ферзь рядом с королём.\n\n> **Вывод:** Угол — самое опасное поле для короля без бегства. Когда ферзь и король сотрудничают на расстоянии в два поля, любое соседнее поле — кандидат на казнь, особенно после взятия последнего щита короля."
}
