{
  "id": "demolition",
  "title": "防壁の破壊(デモリッション)",
  "summary": "敵陣を爆破して開く",
  "difficulty": "intermediate",
  "steps": [
    {
      "type": "teach",
      "fen": "r1bq1rk1/ppp2ppp/2np1n2/2b1p3/2B1P3/2NP1N2/PPP2PPP/R1BQ1RK1 w - - 0 1",
      "title": "殻を割る犠牲",
      "text": "敵キングへの唯一の道がレンガの壁 — つまりキングを覆うポーン群 — を貫いていることがあります。**デモリッション**の犠牲はその壁を打ち砕き、キングを他の駒の前にさらします。\n\n## 古典的なデモリッションのパターン\n\n- **ギリシャの贈り物** — キングサイド・キャスリング後のキングへの{{Bxh7+}};ビショップ犠牲に続いてナイトとクイーンが攻める。\n- **f7のナイト** — {{Nxf7}}でクイーンとルークをフォーク、またはf筋を切り開く。\n- **h6 / f5のナイト** — チェックや重大な脅威でキングのポーン覆いをこじ開ける。\n- **c3 / c6でのエクスチェンジ犠牲** — シシリアン流:ルークをナイトと交換してポーン構造を破壊。\n- **ポーン・ストーム** — 敵キングへ向けてポーンを *突き刺し*、筋と対角線を切り開く。\n\n## 視覚的トリガー\n\n- 敵キングが無傷のポーンに守られて**キャスリング**済み。\n- キングから2手以内に**攻撃役の駒の塊**(クイーン+1〜2枚のマイナー駒)がいる。\n- 守備側に**f6の有用なナイト**(またはその鏡像)がなく、穴を塞げない。\n\n## デモリッションの見つけ方\n\n1. 敵キング近くの攻撃駒を数える。\n2. キングのポーンの盾の*守備駒*を数える。\n3. 攻撃 ≥ 守備 + 1 なら、筋や対角線を開く犠牲を探す。\n4. 詰みまたは勝勢の攻撃まで、少なくとも4〜6手先まで読む。\n\n> 材料は取り戻せます。完全に開かれた敵キングは元には戻せません。\n\nこのイタリアン風の局面では、{{Bxh7+}}は教科書的なギリシャの贈り物の出だしです — どう展開するかは続くレッスンで見ましょう。"
    },
    {
      "type": "teach",
      "fen": "r1bq1rk1/ppp2ppp/2np1n2/2b1p3/2B1P3/2NP1N2/PPP2PPP/R1BQ1RK1 w - - 0 1",
      "title": "破壊するとき(と、しないとき)",
      "text": "デモリッションの犠牲は**読み切って**指すもので、勘で指すものではありません。間違った局面で駒を捨てれば、ただ負けるだけです。\n\n## 三つの前提条件\n\n1. **攻撃役の準備** — クイーンと少なくとも一枚のマイナー駒が2手以内に攻撃に加われる。\n2. **守備駒の不在** — 主要な守備駒(黒なら{{Nf6}}、白なら{{Nf3}}がほぼ常に該当)が消えているか、ピンされている。\n3. **反撃なし** — 相手が自分のキングへより速い攻撃を持っていない。\n\n## 判断のモデル\n\n決断する前に:\n\n- **強制**手を5手以上先まで読む。\n- 各分岐で問う:*キングへの攻撃役を維持できているか?*\n- 読みの末端で**詰みの脅威か千日手**を探す。\n\n## 引き返すべきとき\n\n- クイーンが遠く、ルーク・リフトが遅い。\n- 守備側に取り除けない要の駒がある。\n- 相手の反撃の脅威(パスポーンやディスカバード・アタックなど)が先に決まる。\n\n> キングを仕留め損ねたデモリッションは、代わりに自分を仕留めます。"
    }
  ]
}
