{
  "id": "endgame-04",
  "fen": "8/8/5k2/8/4K3/4P3/8/8 w - - 0 1",
  "solution": [
    "Kd5"
  ],
  "title": "王活跃即胜",
  "setup": "兵在 **e3**，王在 **e4**，黑王坐在 f6 试图盯住兵的升变格。",
  "hint": "别直接向前——走到一个敌王够不到的格子，**抢占地盘**。",
  "explanation": "## 关键原则：用王赢得格子\n\n黑王正在尽职：覆盖 e5、e6 和 e7，拖慢你的兵。要取得进展，你的王必须到达第 6 横线，又不能让自己被赶走。办法是**斜向前进**，到一个敌王无法立即争夺的格子。\n\n## 计划\n\n1. **{{Kd5}}** —— 白方向后翼推进，赢一横线，且不站在黑方能立即挑战的格子上。黑方不能 Kd5（被占）、Ke5（被你王攻击）、Kf5（被攻击）。\n2. 黑方最佳尝试是 **...Ke7**，匆匆回防。白方答以 **Kc6** 或 **Ke5**，继续推开敌王同时保护兵。\n3. 当白王到达第 6 横线，兵开始行进：**e4、e5、e6** —— 然后王让出升变格。\n\n## 推兵会怎样？\n\n如果白方立刻 1.e4？，f6 的王此时位置极佳：1...Ke6！黑方就守住了**兵前方的格子**。从那里它就是堡垒——和棋。启示：**推兵之前，先赢得兵将站立的格子**。"
}
