{
  "id": "mate-in-1-19",
  "fen": "Q7/5Bpk/7p/8/8/8/8/7K w - - 0 1",
  "solution": [
    "Qg8#"
  ],
  "title": "象给后撑腰",
  "setup": "黑王困在 **h7**，身后还压着 **h6** 兵；你 **f7** 的象从斜线锁死了 {{g8}}。",
  "hint": "把后送到 {{g8}} —— **f7** 的象守着她的落点。",
  "explanation": "## 思路\n\n一道**后象贴脸杀**。**f7** 的象把 g8 变成了一个被守住的格子，后就敢牺牲似地送进去。\n\n走 {{Qg8#}}。\n\n王为何动弹不得？\n\n- g8 上的后直接攻击 h7（斜线将军，由象保护）\n- {{Kxg8}} 非法 —— **f7** 的象守着 g8\n- {{h8}} —— 由 g8 上的后控制\n- 王不能吃 f7 的象：王正被将军，必须先解将\n- 黑方没有别的子能介入\n\n> **经验：** 一只距离底线只差一步的象，可以为后的杀棋牺牲撑腰。每当你的后和象都靠近敌王时，扫一眼有没有一个紧挨着王、又被己方守护的落点。"
}
