{
  "id": "gruenfeld-advanced",
  "title": "格林菲尔德防御",
  "summary": "反击型超现代体系",
  "difficulty": "advanced",
  "steps": [
    {
      "type": "teach",
      "fen": "rnbqkb1r/ppp1pp1p/5np1/3p4/2PP4/2N5/PP2PPPP/R1BQKBNR w KQkq - 0 4",
      "title": "让他们过度扩张",
      "text": "**格林菲尔德防御**是反击者的杰作 —— 一个超现代派开局，黑方*邀请*白方建大中心，明知它难以守住。\n\n它得名于 1920 年代提出该体系的奥地利大师 **恩斯特·格林菲尔德**，曾在 **鲍比·费舍尔**、**弗拉基米尔·克拉姆尼克**、**加里·卡斯帕罗夫**、**马格努斯·卡尔森** 职业生涯的不同阶段成为他们的主武器。\n\n## 怎么走到\n\n标志性序列：{{d4}} **{{Nf6}}** {{c4}} **{{g6}}** {{Nc3}} **{{d5}}**。无所畏惧的 **3...d5** 是体系的灵魂：黑方一边直接挑战白方的 c 兵，一边为翼角化做准备。\n\n## 双方各想做什么\n\n- **白方计划：** 在中心用 **{{cxd5}} {{Nxd5}} {{e4}}** 吃子（兑换变例），或用 {{Nf3}}、{{Bf4}}、{{e3}}、{{Be2}} 安静发展（俄罗斯体系），或 {{Bg5}}（斯梅斯洛夫体系）。目标是建立并*守住*大中心。\n- **黑方计划：** 把王翼象翼角化到 **g7**，用 **...c5** 攻击 d4，有时用 **...e5** 突破，发展 **...Nc6**、**...Bg4**，证明白方的中心是*过度扩张*。\n- **兵形结构：** 标志性的格林菲尔德不平衡 —— 白方在 d4、e4 有中央兵（兑换变例），黑方兵少但子力极活跃。\n\n## 为什么大胆\n\n格林菲尔德主动让出**中心**。黑方赌白方的兵会变成*靶子*而不是武器。如果黑方赌对了，白方大中心崩塌；赌错了，黑方被压扁。\n\n> 格林菲尔德像爵士乐：在复杂主题上的即兴。一旦奏响，就美得难以置信。"
    },
    {
      "type": "teach",
      "fen": "rnbqkb1r/ppp1pp1p/5np1/3P4/2P5/2N5/PP2PPPP/R1BQKBNR b KQkq - 0 4",
      "title": "兑换变例",
      "text": "白方最常见的应手是**兑换变例** —— **4.cxd5 Nxd5 5.e4**。黑方的马撤退，白方中心现在有*两*只中央兵（d4 和 e4）。\n\n## 为什么这是关键\n\n- 白方的兵看着吓人 —— 把黑方的子力切成两半，似乎统治整个棋盘。\n- 但兵就是**兵** —— 可以被攻击。子力则灵活。\n- 黑方计划 **...Bg7**、**...c5**（打 d4）、**...Nc6**、**...Qa5** 或 **...Bg4** —— 全力围攻中心。\n\n## 现代兑换变例\n\n著名的主线：**5.e4 Nxc3 6.bxc3 Bg7 7.Nf3 c5 8.Be3 Qa5 9.Qd2 Nc6** —— 第 9 步时，黑方已发展完毕、攻击中心、随时用 **...cxd4** 突破瓦解白方结构。\n\n## 结构告诉我们什么\n\n- 白方的**孤立 d 兵或叠 c 兵**会成为长期靶子。\n- 黑方的**翼角 g7 象**统治长斜线 —— 同时盯着 **a1、b2、c3、d4**。\n- **c5 突破** 是黑方的标志性着法 —— 没有它，格林菲尔德毫无作为。\n\n## 白方其他尝试\n\n- **俄罗斯体系**（4.Nf3 Bg7 5.Qb3）—— 白方用后压 d5。\n- **Bg5 / 斯梅斯洛夫体系** —— 白方早早出象，劝阻 ...c5。\n- **萨米施 / 塔尔塔科尔** —— 白方走 {{f3}} 准备 e4。\n\n> 兑换变例格林菲尔德：白方建房，黑方狙击。"
    },
    {
      "type": "teach",
      "fen": "rnbqkb1r/ppp1pp1p/5np1/3p4/2PP4/2N5/PP2PPPP/R1BQKBNR w KQkq - 0 4",
      "title": "古典格林菲尔德主题",
      "text": "格林菲尔德有一小套反复出现的战略主题。掌握它们，几乎任何格林菲尔德中局你都不会陌生。\n\n## 黑方剧本\n\n- **g7 翼角化。** 这只象是整个开局的引擎。除非万不得已，*绝不*用它换比马更次的东西。\n- **用 ...c5 压 d4。** 这是标志性突破。没有它，白方中心太强。\n- **短易位** —— 通常第 6 或第 7 步。翼角象与易位后的王构成防守三角。\n- **...Nc6、...Bg4、...Qa5。** 子力瞄向中央兵和 c3 的马（被迫同时守 d4 和 e4，过度负担）。\n- **...Rfd8、...Rac8。** 出子完毕后，车堆到 c 线和 d 线 —— 结构博弈的主战场。\n\n## d4-d5 赛跑\n\n许多格林菲尔德对局的关键问题：*黑方能否逼 d4 推到 d5？* 能 —— 黑方就能从 c6 和 e6 攻击如今孤立的 d5 兵。不能 —— 白方中心完整，双象加空间继续起作用。\n\n## 著名格林菲尔德棋局\n\n- **博特维尼克–费舍尔 1962** —— 费舍尔用格林菲尔德以惊艳风格摧毁世界冠军。\n- **卡斯帕罗夫–卡尔波夫 1990 世界冠军赛** —— 卡斯帕罗夫多次用格林菲尔德获胜，改写了主流理论。\n- **卡尔森–阿南德 2014** —— 阿南德的格林菲尔德是奇袭开局选择，让卡尔森冒了汗。\n\n> 格林菲尔德：小子力，大思想。把反击当成一种生活方式。"
    }
  ]
}
