{
  "id": "bishop-pair",
  "title": "双象",
  "summary": "双象的价值超乎你的想象",
  "difficulty": "intermediate",
  "steps": [
    {
      "type": "teach",
      "fen": "rnbqkbnr/pppppppp/8/8/8/8/PPPPPPPP/RNBQKBNR w KQkq - 0 1",
      "title": "为什么是双象?",
      "text": "## 双象——定义\n\n**双象**是国际象棋中最稳定的长期优势之一。两只象配在一起的价值,大约比两只马或马 + 象的组合多 **+0.5** 个兵——拉里·考夫曼在数百万局棋的统计研究中确认了这个名义价值。\n\n### 为什么\"双象\"大于两只象之和\n\n- 每只象只覆盖**自己颜色**的格子。**两只象一起**覆盖**全部 64 格**。\n- 它们**互补**: 黑格象守白格象守不到的格子,反之亦然。\n- 在**长距离**上协同——比两只马在开放局面里好得多。\n- 在残局中**转化优势**更可靠,因为空间和先手都更具决定性。\n\n### 两个直观例子\n\n- *开放残局*: 白方双象,后翼对王翼兵都全在场。白格象在一翼封锁,黑格象沿长对角线走向王翼。对手的双马跟不上节奏。\n- *安静的中局*: 中心张力解开、兵形对称时,白方在 **b2** 与 **c4** 的双象长程瞄准黑王 g8。双象 + 后的进攻动机(*翼侧 + 意大利*重炮)极具杀伤力。\n\n### 如何运用双象\n\n1. **打开局面**——双象在开放对局中大放异彩。换兵,不要换子。\n2. 不要随便**换掉任何一只象**,除非换得更好(如换掉对方一只强马)。\n3. 把象放在**长且有争夺的对角线**——绝不放在短对角线上。\n4. 在**残局**中施压——子越少,双象的价值越高。\n\n### 哪些信号提示双象具有决定性\n\n- 局面**简单且开放**。\n- 对方有一只**没有据点**的马。\n- **两翼都有兵**——双象都能到达,马则不能。\n\n### 常见错误\n\n- 在封闭局面中**消极地保留双象**——封闭局面有利于马。\n- 为了赢一个兵而**换掉一只象**换马——往往是错误的子力平衡。\n- 忘了**异色象残局**会抵消双象的价值(在那里,只有一种颜色的象起作用)。\n\n> 双象,一种战略: 打开棋盘,让它们歌唱。"
    },
    {
      "type": "teach",
      "fen": "rnbqkbnr/pppppppp/8/8/8/8/PPPPPPPP/RNBQKBNR w KQkq - 0 1",
      "title": "何时交换",
      "text": "## 双象中局的交换规则\n\n在任何双象中局里,最有用的问题是:**\"哪个交换对我有利?\"** 答案遵循两条简单的规则。\n\n### 规则 1 —— 如果你**拥有**双象\n\n1. **打开局面**: 交换兵以打开线。\n2. **拒绝**涉及一只象的轻子交换。如果对方提出 Bxc6,可能就拒绝。\n3. **交换其他子**(如果一定要交换)——有时甚至包括后。\n4. **避免**给对方制造马的据点。封闭局面有利于马,不利于象。\n\n### 规则 2 —— 如果你**放弃了**双象\n\n1. **封闭局面**: 让兵互相咬合,拒绝打开线的兵交换。\n2. **争取一个马的据点**,最好在 5 线或 6 线。\n3. **换掉对方的好象**——把坏象留给他。\n4. **把兵推到对方剩下那只象的颜色上**,让它变坏。\n\n### 两个直观例子\n\n- *西班牙交换变*: 白方主动走 {{Bxc6}}。黑方得到双象,但出现**叠 c 兵**。白方的计划是**简化进残局**,在那里叠兵的影响超过双象。\n- *尼姆佐-印度萨米什变*: 白方走 {{f3}} 与 {{e4}} 拥有双象,但中心封闭,c 列叠兵且弱。黑方目标是 ...c5、封锁,凭结构补偿撑住,即使没有双象。\n\n### 如何运用这些规则\n\n1. **第 15 步前决定**哪一方想要双象,哪一方想要封闭中心。\n2. 让每一步**兵的着法**都与该决定一致。\n3. 按规则**交换或拒绝交换**——这里哪怕一点不准也可能颠覆胜局。\n\n### 哪些信号提示你应用此规则\n\n- 你**双象** vs **象 + 马** 或 **双马**。\n- 对方刚刚走了一步**会换进马据点**的着法——拒绝它。\n- 局面**即将打开**(兵的突破)——你有双象就接受;没有就阻止。\n\n### 常见错误\n\n- 为了**眼前小利益**过早换掉双象。\n- 为了\"保护\"双象而**封闭自己的局面**——你把它们闷死了。\n- 放弃双象时**忽视结构代价**——哪怕一步先手补偿都可能不够。\n\n> 双象只买一次,只卖一次。慎重选择。"
    }
  ]
}
